print_project.py
reconstruct_project.py
print_project-2.2.1.dist-info/LICENSE
print_project-2.2.1.dist-info/METADATA
print_project-2.2.1.dist-info/WHEEL
print_project-2.2.1.dist-info/entry_points.txt
print_project-2.2.1.dist-info/top_level.txt
print_project-2.2.1.dist-info/RECORD
