Metadata-Version: 2.1
Name: print-project
Version: 2.2.1
Summary: Directory Content Analysis Tool - Extract and analyze source code files across project structures
Author-email: smaxiso <smaxiso@users.noreply.github.com>
License: MIT License
Project-URL: Homepage, https://github.com/smaxiso/print-project
Project-URL: Repository, https://github.com/smaxiso/print-project
Project-URL: Issues, https://github.com/smaxiso/print-project/issues
Project-URL: Changelog, https://github.com/smaxiso/print-project/blob/master/docs/CHANGELOG.md
Project-URL: Documentation, https://github.com/smaxiso/print-project/blob/master/README.md
Project-URL: Bug Reports, https://github.com/smaxiso/print-project/issues
Project-URL: Source Code, https://github.com/smaxiso/print-project
Keywords: code-analysis,directory-scanner,documentation,source-code,project-analysis
Classifier: Development Status :: 5 - Production/Stable
Classifier: Intended Audience :: Developers
Classifier: License :: OSI Approved :: MIT License
Classifier: Programming Language :: Python :: 3
Classifier: Programming Language :: Python :: 3.6
Classifier: Programming Language :: Python :: 3.7
Classifier: Programming Language :: Python :: 3.8
Classifier: Programming Language :: Python :: 3.9
Classifier: Programming Language :: Python :: 3.10
Classifier: Programming Language :: Python :: 3.11
Classifier: Programming Language :: Python :: 3.12
Classifier: Topic :: Software Development :: Documentation
Classifier: Topic :: Software Development :: Libraries :: Python Modules
Classifier: Topic :: System :: Filesystems
Classifier: Topic :: Utilities
Requires-Python: >=3.6
License-File: LICENSE
Requires-Dist: chardet>=3.0.4
Provides-Extra: dev
Requires-Dist: pytest>=6.0; extra == "dev"
Requires-Dist: black>=21.0; extra == "dev"
Requires-Dist: flake8>=3.8; extra == "dev"
Requires-Dist: mypy>=0.800; extra == "dev"
